genpass/__init__.py
genpass/core.py
genpass_cli-1.0.0.dist-info/LICENSE
genpass_cli-1.0.0.dist-info/METADATA
genpass_cli-1.0.0.dist-info/WHEEL
genpass_cli-1.0.0.dist-info/entry_points.txt
genpass_cli-1.0.0.dist-info/top_level.txt
genpass_cli-1.0.0.dist-info/RECORD
