Metadata-Version: 2.1
Name: genpass-cli
Version: 1.0.0
Summary: A simple yet powerful password generator
Home-page: https://github.com/tahzeer/genpass-cli
Author: tahzeer
Author-email: tahzeer.work@gmail.com
Classifier: Programming Language :: Python :: 3
Classifier: License :: OSI Approved :: MIT License
Classifier: Operating System :: OS Independent
Requires-Python: >=3.6
License-File: LICENSE
Requires-Dist: pyperclip>=1.8.2
